[{"outer": "coat", "outercol": "brown", "top": "long blouse", "topcol": "brown", "url": "https://smart-wardrobe-static.s3.amazonaws.com/mss/man/formal/13605.jpg"}, {"bottom": "chinos", "bottomcol": "darkgray", "url": "https://smart-wardrobe-static.s3.amazonaws.com/mss/man/formal/13636.jpg"}, {"bottom": "chinos", "bottomcol": "black", "outer": "bomber", "outercol": "darkgray", "top": "long blouse", "topcol": "darkgray", "url": "https://smart-wardrobe-static.s3.amazonaws.com/mss/man/formal/13637.jpg"}, {"outer": "cardigan", "outercol": "brown", "top": "long blouse", "topcol": "beige", "bottom": "chinos", "bottomcol": "brown", "url": "https://smart-wardrobe-static.s3.amazonaws.com/mss/man/formal/13691.jpg"}, {"outer": "coat", "outercol": "brown", "top": "long shirt", "topcol": "brown", "bottom": "chinos", "bottomcol": "brown", "url": "https://smart-wardrobe-static.s3.amazonaws.com/mss/man/formal/13725.jpg"}, {"outer": "coat", "outercol": "navy", "top": "long tee", "topcol": "blue", "url": "https://smart-wardrobe-static.s3.amazonaws.com/mss/man/formal/13781.jpg"}, {"bottom": "chinos", "bottomcol": "brown", "url": "https://smart-wardrobe-static.s3.amazonaws.com/mss/man/formal/13795.jpg"}, {"bottom": "chinos", "bottomcol": "darkgray", "outer": "parka", "outercol": "black", "top": "long shirt", "topcol": "lightgray", "url": "https://smart-wardrobe-static.s3.amazonaws.com/mss/man/formal/13798.jpg"}, {"bottom": "chinos", "bottomcol": "black", "url": "https://smart-wardrobe-static.s3.amazonaws.com/mss/man/formal/13810.jpg"}, {"bottom": "chinos", "bottomcol": "black", "url": "https://smart-wardrobe-static.s3.amazonaws.com/mss/man/formal/13854.jpg"}, {"bottom": "chinos", "bottomcol": "black", "outer": "leather", "outercol": "black", "top": "long shirt", "topcol": "lightgray", "url": "https://smart-wardrobe-static.s3.amazonaws.com/mss/man/formal/13870.jpg"}, {"bottom": "chinos", "bottomcol": "darkgray", "outer": "bomber", "outercol": "darkgray", "top": "long shirt", "topcol": "lightgray", "url": "https://smart-wardrobe-static.s3.amazonaws.com/mss/man/formal/13904.jpg"}, {"bottom": "chinos", "bottomcol": "beige", "outer": "bomber", "outercol": "darkgray", "top": "long tee", "topcol": "beige", "url": "https://smart-wardrobe-static.s3.amazonaws.com/mss/man/formal/13908.jpg"}, {"bottom": "chinos", "bottomcol": "brown", "outer": "coat", "outercol": "olive", "top": "long shirt", "topcol": "beige", "url": "https://smart-wardrobe-static.s3.amazonaws.com/mss/man/formal/13931.jpg"}, {"bottom": "chinos", "bottomcol": "beige", "outer": "blazer", "outercol": "brown", "top": "long blouse", "topcol": "lightgray", "url": "https://smart-wardrobe-static.s3.amazonaws.com/mss/man/formal/13932.jpg"}, {"bottom": "chinos", "bottomcol": "darkgray", "outer": "cardigan", "outercol": "darkgray", "top": "long blouse", "topcol": "darkgray", "url": "https://smart-wardrobe-static.s3.amazonaws.com/mss/man/formal/13935.jpg"}, {"bottom": "chinos", "bottomcol": "lightgray", "outer": "blazer", "outercol": "black", "top": "long shirt", "topcol": "lightgray", "url": "https://smart-wardrobe-static.s3.amazonaws.com/mss/man/formal/13936.jpg"}, {"bottom": "chinos", "bottomcol": "darkgray", "outer": "bomber", "outercol": "navy", "top": "long blouse", "topcol": "darkgray", "url": "https://smart-wardrobe-static.s3.amazonaws.com/mss/man/formal/13937.jpg"}, {"bottom": "chinos", "bottomcol": "navy", "outer": "blazer", "outercol": "darkgray", "top": "long shirt", "topcol": "lightgray", "url": "https://smart-wardrobe-static.s3.amazonaws.com/mss/man/formal/13938.jpg"}, {"bottom": "chinos", "bottomcol": "black", "outer": "blazer", "outercol": "black", "top": "long shirt", "topcol": "beige", "url": "https://smart-wardrobe-static.s3.amazonaws.com/mss/man/formal/13939.jpg"}, {"bottom": "chinos", "bottomcol": "brown", "outer": "trench coat", "outercol": "brown", "top": "long blouse", "topcol": "brown", "url": "https://smart-wardrobe-static.s3.amazonaws.com/mss/man/formal/13941.jpg"}, {"bottom": "chinos", "bottomcol": "lightgray", "outer": "trench coat", "outercol": "darkgray", "top": "long shirt", "topcol": "lightgray", "url": "https://smart-wardrobe-static.s3.amazonaws.com/mss/man/formal/13942.jpg"}, {"bottom": "chinos", "bottomcol": "navy", "outer": "trench coat", "outercol": "darkgray", "top": "long shirt", "topcol": "darkgray", "url": "https://smart-wardrobe-static.s3.amazonaws.com/mss/man/formal/13943.jpg"}, {"bottom": "jeans", "bottomcol": "jean", "outer": "coat", "outercol": "brown", "top": "long tee", "topcol": "beige", "url": "https://smart-wardrobe-static.s3.amazonaws.com/mss/man/formal/13949.jpg"}, {"bottom": "chinos", "bottomcol": "blue", "outer": "blazer", "outercol": "brown", "top": "long blouse", "topcol": "lightgray", "url": "https://smart-wardrobe-static.s3.amazonaws.com/mss/man/formal/13950.jpg"}, {"bottom": "chinos", "bottomcol": "darkgray", "outer": "parka", "outercol": "olive", "top": "long shirt", "topcol": "beige", "url": "https://smart-wardrobe-static.s3.amazonaws.com/mss/man/formal/13951.jpg"}, {"bottom": "chinos", "bottomcol": "black", "outer": "blazer", "outercol": "lightgray", "top": "long tee", "topcol": "darkgray", "url": "https://smart-wardrobe-static.s3.amazonaws.com/mss/man/formal/14019.jpg"}, {"outer": "trench coat", "outercol": "darkgray", "top": "long shirt", "topcol": "beige", "bottom": "chinos", "bottomcol": "beige", "url": "https://smart-wardrobe-static.s3.amazonaws.com/mss/man/formal/14022.jpg"}, {"bottom": "chinos", "bottomcol": "pink", "url": "https://smart-wardrobe-static.s3.amazonaws.com/mss/man/formal/14025.jpg"}, {"outer": "coat", "outercol": "black", "top": "long shirt", "topcol": "darkgray", "url": "https://smart-wardrobe-static.s3.amazonaws.com/mss/man/formal/14080.jpg"}, {"bottom": "chinos", "bottomcol": "beige", "url": "https://smart-wardrobe-static.s3.amazonaws.com/mss/man/formal/14085.jpg"}, {"bottom": "chinos", "bottomcol": "beige", "url": "https://smart-wardrobe-static.s3.amazonaws.com/mss/man/formal/14095.jpg"}, {"bottom": "jeans", "bottomcol": "lightjean", "outer": "leather", "outercol": "darkgray", "top": "long shirt", "topcol": "lightgray", "url": "https://smart-wardrobe-static.s3.amazonaws.com/mss/man/formal/14122.jpg"}, {"bottom": "long skirt", "bottomcol": "beige", "top": "long tee", "topcol": "lightgray", "url": "https://smart-wardrobe-static.s3.amazonaws.com/mss/man/formal/14153.jpg"}, {"bottom": "chinos", "bottomcol": "darkgray", "outer": "coat", "outercol": "beige", "top": "long shirt", "topcol": "beige", "url": "https://smart-wardrobe-static.s3.amazonaws.com/mss/man/formal/14275.jpg"}, {"bottom": "chinos", "bottomcol": "darkgray", "url": "https://smart-wardrobe-static.s3.amazonaws.com/mss/man/formal/14278.jpg"}, {"bottom": "chinos", "bottomcol": "darkgray", "url": "https://smart-wardrobe-static.s3.amazonaws.com/mss/man/formal/14280.jpg"}, {"bottom": "chinos", "bottomcol": "darkgray", "outer": "blazer", "outercol": "darkgray", "top": "long shirt", "topcol": "lightgray", "url": "https://smart-wardrobe-static.s3.amazonaws.com/mss/man/formal/14330.jpg"}, {"bottom": "chinos", "bottomcol": "lightgray", "outer": "trench coat", "outercol": "darkgray", "top": "long blouse", "topcol": "beige", "url": "https://smart-wardrobe-static.s3.amazonaws.com/mss/man/formal/14332.jpg"}, {"bottom": "chinos", "bottomcol": "darkgray", "outer": "trench coat", "outercol": "beige", "top": "long shirt", "topcol": "beige", "url": "https://smart-wardrobe-static.s3.amazonaws.com/mss/man/formal/14335.jpg"}, {"bottom": "jeans", "bottomcol": "lightjean", "outer": "coat", "outercol": "beige", "top": "long shirt", "topcol": "lightgray", "url": "https://smart-wardrobe-static.s3.amazonaws.com/mss/man/formal/14342.jpg"}, {"bottom": "chinos", "bottomcol": "brown", "outer": "trench coat", "outercol": "beige", "top": "long shirt", "topcol": "beige", "url": "https://smart-wardrobe-static.s3.amazonaws.com/mss/man/formal/14446.jpg"}, {"bottom": "shorts", "bottomcol": "beige", "url": "https://smart-wardrobe-static.s3.amazonaws.com/mss/man/formal/14449.jpg"}, {"bottom": "chinos", "bottomcol": "darkgray", "outer": "trench coat", "outercol": "lightgray", "top": "long shirt", "topcol": "purple", "url": "https://smart-wardrobe-static.s3.amazonaws.com/mss/man/formal/14451.jpg"}, {"bottom": "chinos", "bottomcol": "darkgray", "outer": "blazer", "outercol": "darkgray", "top": "long shirt", "topcol": "lightgray", "url": "https://smart-wardrobe-static.s3.amazonaws.com/mss/man/formal/14454.jpg"}, {"bottom": "chinos", "bottomcol": "beige", "outer": "blazer", "outercol": "beige", "top": "long shirt", "topcol": "white", "url": "https://smart-wardrobe-static.s3.amazonaws.com/mss/man/formal/14555.jpg"}, {"dress": "jumpsuit", "dresscol": "darkgray", "top": "long tee", "topcol": "darkgray", "url": "https://smart-wardrobe-static.s3.amazonaws.com/mss/man/formal/14559.jpg"}, {"bottom": "chinos", "bottomcol": "navy", "top": "long tee", "topcol": "beige", "url": "https://smart-wardrobe-static.s3.amazonaws.com/mss/man/formal/14595.jpg"}, {"bottom": "chinos", "bottomcol": "darkgray", "outer": "trench coat", "outercol": "beige", "top": "long shirt", "topcol": "lightgray", "url": "https://smart-wardrobe-static.s3.amazonaws.com/mss/man/formal/14712.jpg"}, {"bottom": "chinos", "bottomcol": "darkgray", "outer": "trench coat", "outercol": "lightgray", "top": "long shirt", "topcol": "lightgray", "url": "https://smart-wardrobe-static.s3.amazonaws.com/mss/man/formal/14714.jpg"}, {"bottom": "chinos", "bottomcol": "darkgray", "outer": "bomber", "outercol": "beige", "top": "long shirt", "topcol": "lightgray", "url": "https://smart-wardrobe-static.s3.amazonaws.com/mss/man/formal/14715.jpg"}, {"bottom": "chinos", "bottomcol": "lightgray", "top": "long shirt", "topcol": "lightgray", "url": "https://smart-wardrobe-static.s3.amazonaws.com/mss/man/formal/14735.jpg"}, {"bottom": "chinos", "bottomcol": "darkgray", "top": "long shirt", "topcol": "white", "url": "https://smart-wardrobe-static.s3.amazonaws.com/mss/man/formal/14736.jpg"}, {"bottom": "sweatpants", "bottomcol": "darkgray", "outer": "blazer", "outercol": "darkgray", "top": "long blouse", "topcol": "lightgray", "url": "https://smart-wardrobe-static.s3.amazonaws.com/mss/man/formal/14799.jpg"}, {"bottom": "chinos", "bottomcol": "darkgray", "outer": "trench coat", "outercol": "black", "top": "long shirt", "topcol": "darkgray", "url": "https://smart-wardrobe-static.s3.amazonaws.com/mss/man/formal/14804.jpg"}, {"bottom": "short skirt", "bottomcol": "black", "top": "long tee", "topcol": "beige", "url": "https://smart-wardrobe-static.s3.amazonaws.com/mss/man/formal/14899.jpg"}, {"bottom": "chinos", "bottomcol": "lightgray", "outer": "bomber", "outercol": "olive", "top": "long shirt", "topcol": "lightgray", "url": "https://smart-wardrobe-static.s3.amazonaws.com/mss/man/formal/14903.jpg"}, {"bottom": "chinos", "bottomcol": "black", "url": "https://smart-wardrobe-static.s3.amazonaws.com/mss/man/formal/14908.jpg"}, {"bottom": "chinos", "bottomcol": "black", "outer": "blazer", "outercol": "darkgray", "top": "long shirt", "topcol": "lightgray", "url": "https://smart-wardrobe-static.s3.amazonaws.com/mss/man/formal/14915.jpg"}, {"bottom": "chinos", "bottomcol": "darkgray", "url": "https://smart-wardrobe-static.s3.amazonaws.com/mss/man/formal/14916.jpg"}, {"bottom": "chinos", "bottomcol": "beige", "url": "https://smart-wardrobe-static.s3.amazonaws.com/mss/man/formal/14921.jpg"}, {"bottom": "chinos", "bottomcol": "darkgray", "top": "long tee", "topcol": "lightgray", "url": "https://smart-wardrobe-static.s3.amazonaws.com/mss/man/formal/15045.jpg"}, {"bottom": "chinos", "bottomcol": "darkgray", "outer": "cardigan", "outercol": "green", "top": "long shirt", "topcol": "lightgray", "url": "https://smart-wardrobe-static.s3.amazonaws.com/mss/man/formal/15051.jpg"}, {"bottom": "jeans", "bottomcol": "darkjean", "outer": "blazer", "outercol": "darkgray", "top": "long tee", "topcol": "lightgray", "url": "https://smart-wardrobe-static.s3.amazonaws.com/mss/man/formal/15056.jpg"}, {"bottom": "chinos", "bottomcol": "black", "outer": "blazer", "outercol": "darkgray", "top": "long shirt", "topcol": "black", "url": "https://smart-wardrobe-static.s3.amazonaws.com/mss/man/formal/15081.jpg"}, {"bottom": "chinos", "bottomcol": "beige", "url": "https://smart-wardrobe-static.s3.amazonaws.com/mss/man/formal/15156.jpg"}, {"bottom": "jeans", "bottomcol": "jean", "outer": "cardigan", "outercol": "beige", "top": "long shirt", "topcol": "white", "url": "https://smart-wardrobe-static.s3.amazonaws.com/mss/man/formal/15157.jpg"}, {"bottom": "chinos", "bottomcol": "lightgray", "top": "long tee", "topcol": "lightgray", "url": "https://smart-wardrobe-static.s3.amazonaws.com/mss/man/formal/15161.jpg"}, {"bottom": "chinos", "bottomcol": "darkgray", "outer": "blazer", "outercol": "darkgray", "top": "long shirt", "topcol": "beige", "url": "https://smart-wardrobe-static.s3.amazonaws.com/mss/man/formal/15162.jpg"}, {"bottom": "chinos", "bottomcol": "darkgray", "outer": "bomber", "outercol": "darkgray", "top": "turtleneck", "topcol": "lightgray", "url": "https://smart-wardrobe-static.s3.amazonaws.com/mss/man/formal/15172.jpg"}, {"bottom": "chinos", "bottomcol": "darkgray", "outer": "bomber", "outercol": "beige", "top": "long tee", "topcol": "darkgray", "url": "https://smart-wardrobe-static.s3.amazonaws.com/mss/man/formal/15175.jpg"}, {"bottom": "chinos", "bottomcol": "darkgray", "url": "https://smart-wardrobe-static.s3.amazonaws.com/mss/man/formal/15190.jpg"}, {"bottom": "chinos", "bottomcol": "darkgray", "top": "long shirt", "topcol": "purple", "url": "https://smart-wardrobe-static.s3.amazonaws.com/mss/man/formal/15191.jpg"}, {"bottom": "chinos", "bottomcol": "lightgray", "top": "long tee", "topcol": "lightgray", "url": "https://smart-wardrobe-static.s3.amazonaws.com/mss/man/formal/15193.jpg"}, {"bottom": "sweatpants", "bottomcol": "darkgray", "top": "long tee", "topcol": "blue", "url": "https://smart-wardrobe-static.s3.amazonaws.com/mss/man/formal/15200.jpg"}, {"bottom": "short skirt", "bottomcol": "darkgray", "outer": "bomber", "outercol": "lightgray", "top": "long shirt", "topcol": "lightgray", "url": "https://smart-wardrobe-static.s3.amazonaws.com/mss/man/formal/15203.jpg"}, {"url": "https://smart-wardrobe-static.s3.amazonaws.com/mss/man/formal/15217.jpg"}, {"bottom": "jeans", "bottomcol": "lightjean", "top": "long tee", "topcol": "beige", "url": "https://smart-wardrobe-static.s3.amazonaws.com/mss/man/formal/15302.jpg"}, {"bottom": "chinos", "bottomcol": "darkgray", "top": "long tee", "topcol": "beige", "url": "https://smart-wardrobe-static.s3.amazonaws.com/mss/man/formal/15304.jpg"}, {"bottom": "chinos", "bottomcol": "darkgray", "top": "long blouse", "topcol": "lightgray", "url": "https://smart-wardrobe-static.s3.amazonaws.com/mss/man/formal/15305.jpg"}, {"bottom": "chinos", "bottomcol": "darkgray", "outer": "bomber", "outercol": "darkgray", "top": "long shirt", "topcol": "white", "url": "https://smart-wardrobe-static.s3.amazonaws.com/mss/man/formal/15306.jpg"}, {"bottom": "chinos", "bottomcol": "darkgray", "top": "long shirt", "topcol": "blue", "url": "https://smart-wardrobe-static.s3.amazonaws.com/mss/man/formal/15307.jpg"}, {"outer": "bomber", "outercol": "darkgray", "top": "long shirt", "topcol": "lightgray", "bottom": "chinos", "bottomcol": "black", "url": "https://smart-wardrobe-static.s3.amazonaws.com/mss/man/formal/15340.jpg"}, {"bottom": "sweatpants", "bottomcol": "darkgray", "top": "short shirt", "topcol": "white", "url": "https://smart-wardrobe-static.s3.amazonaws.com/mss/man/formal/15493.jpg"}, {"top": "long shirt", "topcol": "lightgray", "bottom": "shorts", "bottomcol": "darkgray", "url": "https://smart-wardrobe-static.s3.amazonaws.com/mss/man/formal/15500.jpg"}, {"bottom": "chinos", "bottomcol": "darkgray", "top": "long shirt", "topcol": "blue", "url": "https://smart-wardrobe-static.s3.amazonaws.com/mss/man/formal/15501.jpg"}, {"bottom": "long skirt", "bottomcol": "blue", "top": "long shirt", "topcol": "darkgray", "url": "https://smart-wardrobe-static.s3.amazonaws.com/mss/man/formal/15545.jpg"}, {"bottom": "sweatpants", "bottomcol": "purple", "top": "short shirt", "topcol": "lightgray", "url": "https://smart-wardrobe-static.s3.amazonaws.com/mss/man/formal/15681.jpg"}, {"bottom": "chinos", "bottomcol": "darkgray", "top": "long tee", "topcol": "darkgray", "url": "https://smart-wardrobe-static.s3.amazonaws.com/mss/man/formal/15687.jpg"}, {"bottom": "chinos", "bottomcol": "lightgray", "top": "long shirt", "topcol": "lightgray", "url": "https://smart-wardrobe-static.s3.amazonaws.com/mss/man/formal/15688.jpg"}, {"bottom": "chinos", "bottomcol": "black", "top": "short shirt", "topcol": "lightgray", "url": "https://smart-wardrobe-static.s3.amazonaws.com/mss/man/formal/15689.jpg"}, {"bottom": "chinos", "bottomcol": "darkgray", "top": "short shirt", "topcol": "lightgray", "url": "https://smart-wardrobe-static.s3.amazonaws.com/mss/man/formal/15694.jpg"}, {"bottom": "shorts", "bottomcol": "darkgray", "top": "long shirt", "topcol": "lightgray", "url": "https://smart-wardrobe-static.s3.amazonaws.com/mss/man/formal/15751.jpg"}, {"top": "long tee", "topcol": "brown", "url": "https://smart-wardrobe-static.s3.amazonaws.com/mss/man/formal/15753.jpg"}, {"bottom": "chinos", "bottomcol": "lightgray", "top": "long shirt", "topcol": "lightgray", "url": "https://smart-wardrobe-static.s3.amazonaws.com/mss/man/formal/15767.jpg"}, {"top": "long shirt", "topcol": "white", "bottom": "shorts", "bottomcol": "beige", "url": "https://smart-wardrobe-static.s3.amazonaws.com/mss/man/formal/15772.jpg"}, {"bottom": "chinos", "bottomcol": "darkgray", "top": "long shirt", "topcol": "beige", "url": "https://smart-wardrobe-static.s3.amazonaws.com/mss/man/formal/15779.jpg"}, {"bottom": "chinos", "bottomcol": "lightgray", "url": "https://smart-wardrobe-static.s3.amazonaws.com/mss/man/formal/15868.jpg"}, {"bottom": "chinos", "bottomcol": "lightgray", "top": "short tee", "topcol": "lightgray", "url": "https://smart-wardrobe-static.s3.amazonaws.com/mss/man/formal/15869.jpg"}, {"bottom": "shorts", "bottomcol": "darkgray", "top": "short shirt", "topcol": "lightgray", "url": "https://smart-wardrobe-static.s3.amazonaws.com/mss/man/formal/15872.jpg"}, {"top": "long shirt", "topcol": "lightgray", "bottom": "shorts", "bottomcol": "blue", "url": "https://smart-wardrobe-static.s3.amazonaws.com/mss/man/formal/15873.jpg"}, {"bottom": "chinos", "bottomcol": "olive", "top": "long shirt", "topcol": "lightgray", "url": "https://smart-wardrobe-static.s3.amazonaws.com/mss/man/formal/15880.jpg"}, {"bottom": "chinos", "bottomcol": "lightgray", "url": "https://smart-wardrobe-static.s3.amazonaws.com/mss/man/formal/15881.jpg"}, {"top": "long shirt", "topcol": "lightgray", "bottom": "shorts", "bottomcol": "darkgray", "url": "https://smart-wardrobe-static.s3.amazonaws.com/mss/man/formal/15883.jpg"}, {"bottom": "chinos", "bottomcol": "beige", "top": "short shirt", "topcol": "beige", "url": "https://smart-wardrobe-static.s3.amazonaws.com/mss/man/formal/15884.jpg"}, {"bottom": "chinos", "bottomcol": "black", "top": "short shirt", "topcol": "lightgray", "url": "https://smart-wardrobe-static.s3.amazonaws.com/mss/man/formal/15885.jpg"}, {"top": "short tee", "topcol": "lightgray", "bottom": "short skirt", "bottomcol": "brown", "url": "https://smart-wardrobe-static.s3.amazonaws.com/mss/man/formal/16013.jpg"}, {"bottom": "chinos", "bottomcol": "black", "top": "short tee", "topcol": "beige", "url": "https://smart-wardrobe-static.s3.amazonaws.com/mss/man/formal/16016.jpg"}, {"url": "https://smart-wardrobe-static.s3.amazonaws.com/mss/man/formal/16018.jpg"}, {"top": "long shirt", "topcol": "lightgray", "bottom": "short skirt", "bottomcol": "black", "url": "https://smart-wardrobe-static.s3.amazonaws.com/mss/man/formal/16026.jpg"}, {"bottom": "chinos", "bottomcol": "beige", "top": "short tee", "topcol": "lightgray", "url": "https://smart-wardrobe-static.s3.amazonaws.com/mss/man/formal/16029.jpg"}, {"bottom": "shorts", "bottomcol": "beige", "outer": "bomber", "outercol": "olive", "top": "long blouse", "topcol": "lightgray", "url": "https://smart-wardrobe-static.s3.amazonaws.com/mss/man/formal/16030.jpg"}, {"bottom": "chinos", "bottomcol": "beige", "outer": "trench coat", "outercol": "beige", "top": "long shirt", "topcol": "lightgray", "url": "https://smart-wardrobe-static.s3.amazonaws.com/mss/man/formal/16196.jpg"}, {"url": "https://smart-wardrobe-static.s3.amazonaws.com/mss/man/formal/16198.jpg"}, {"bottom": "chinos", "bottomcol": "beige", "top": "short tee", "topcol": "beige", "url": "https://smart-wardrobe-static.s3.amazonaws.com/mss/man/formal/16199.jpg"}, {"bottom": "chinos", "bottomcol": "beige", "top": "short tee", "topcol": "lightgray", "url": "https://smart-wardrobe-static.s3.amazonaws.com/mss/man/formal/16203.jpg"}, {"bottom": "chinos", "bottomcol": "darkgray", "top": "short tee", "topcol": "blue", "url": "https://smart-wardrobe-static.s3.amazonaws.com/mss/man/formal/16277.jpg"}, {"bottom": "chinos", "bottomcol": "beige", "top": "short tee", "topcol": "darkgray", "url": "https://smart-wardrobe-static.s3.amazonaws.com/mss/man/formal/16278.jpg"}, {"url": "https://smart-wardrobe-static.s3.amazonaws.com/mss/man/formal/16279.jpg"}, {"bottom": "shorts", "bottomcol": "black", "outer": "blazer", "outercol": "black", "top": "long blouse", "topcol": "beige", "url": "https://smart-wardrobe-static.s3.amazonaws.com/mss/man/formal/16280.jpg"}, {"bottom": "chinos", "bottomcol": "beige", "top": "long shirt", "topcol": "lightgray", "url": "https://smart-wardrobe-static.s3.amazonaws.com/mss/man/formal/16282.jpg"}, {"top": "short tee", "topcol": "beige", "bottom": "chinos", "bottomcol": "brown", "url": "https://smart-wardrobe-static.s3.amazonaws.com/mss/man/formal/16283.jpg"}, {"bottom": "long skirt", "bottomcol": "lightgray", "url": "https://smart-wardrobe-static.s3.amazonaws.com/mss/man/formal/16284.jpg"}, {"bottom": "chinos", "bottomcol": "black", "top": "short tee", "topcol": "beige", "url": "https://smart-wardrobe-static.s3.amazonaws.com/mss/man/formal/16291.jpg"}, {"bottom": "shorts", "bottomcol": "black", "top": "long shirt", "topcol": "lightgray", "url": "https://smart-wardrobe-static.s3.amazonaws.com/mss/man/formal/16294.jpg"}, {"top": "short tee", "topcol": "green", "bottom": "shorts", "bottomcol": "lightgray", "url": "https://smart-wardrobe-static.s3.amazonaws.com/mss/man/formal/16352.jpg"}, {"bottom": "chinos", "bottomcol": "beige", "top": "short tee", "topcol": "beige", "url": "https://smart-wardrobe-static.s3.amazonaws.com/mss/man/formal/16355.jpg"}, {"bottom": "short skirt", "bottomcol": "darkgray", "url": "https://smart-wardrobe-static.s3.amazonaws.com/mss/man/formal/16357.jpg"}, {"bottom": "shorts", "bottomcol": "black", "top": "short shirt", "topcol": "darkgray", "url": "https://smart-wardrobe-static.s3.amazonaws.com/mss/man/formal/16361.jpg"}, {"top": "short tee", "topcol": "lightgray", "bottom": "chinos", "bottomcol": "darkgray", "url": "https://smart-wardrobe-static.s3.amazonaws.com/mss/man/formal/16479.jpg"}, {"bottom": "jeans", "bottomcol": "lightjean", "top": "short tee", "topcol": "lightgray", "url": "https://smart-wardrobe-static.s3.amazonaws.com/mss/man/formal/16502.jpg"}, {"bottom": "chinos", "bottomcol": "brown", "top": "short tee", "topcol": "black", "url": "https://smart-wardrobe-static.s3.amazonaws.com/mss/man/formal/16563.jpg"}, {"bottom": "chinos", "bottomcol": "lightgray", "top": "long shirt", "topcol": "lightgray", "url": "https://smart-wardrobe-static.s3.amazonaws.com/mss/man/formal/16565.jpg"}, {"bottom": "chinos", "bottomcol": "lightgray", "top": "short tee", "topcol": "lightgray", "url": "https://smart-wardrobe-static.s3.amazonaws.com/mss/man/formal/16575.jpg"}, {"bottom": "chinos", "bottomcol": "black", "top": "short shirt", "topcol": "darkgray", "url": "https://smart-wardrobe-static.s3.amazonaws.com/mss/man/formal/16626.jpg"}, {"bottom": "chinos", "bottomcol": "black", "top": "short shirt", "topcol": "lightgray", "url": "https://smart-wardrobe-static.s3.amazonaws.com/mss/man/formal/16651.jpg"}, {"bottom": "shorts", "bottomcol": "black", "top": "short tee", "topcol": "beige", "url": "https://smart-wardrobe-static.s3.amazonaws.com/mss/man/formal/16680.jpg"}, {"bottom": "chinos", "bottomcol": "black", "top": "short tee", "topcol": "lightgray", "url": "https://smart-wardrobe-static.s3.amazonaws.com/mss/man/formal/16958.jpg"}, {"bottom": "chinos", "bottomcol": "black", "top": "short shirt", "topcol": "beige", "url": "https://smart-wardrobe-static.s3.amazonaws.com/mss/man/formal/17025.jpg"}, {"bottom": "chinos", "bottomcol": "darkgray", "top": "short tee", "topcol": "black", "url": "https://smart-wardrobe-static.s3.amazonaws.com/mss/man/formal/17053.jpg"}, {"bottom": "chinos", "bottomcol": "lightgray", "top": "short tee", "topcol": "blue", "url": "https://smart-wardrobe-static.s3.amazonaws.com/mss/man/formal/17055.jpg"}, {"top": "short shirt", "topcol": "beige", "url": "https://smart-wardrobe-static.s3.amazonaws.com/mss/man/formal/17072.jpg"}, {"bottom": "chinos", "bottomcol": "lightgray", "top": "short shirt", "topcol": "black", "url": "https://smart-wardrobe-static.s3.amazonaws.com/mss/man/formal/17103.jpg"}, {"bottom": "chinos", "bottomcol": "beige", "top": "short shirt", "topcol": "green", "url": "https://smart-wardrobe-static.s3.amazonaws.com/mss/man/formal/17113.jpg"}, {"bottom": "sweatpants", "bottomcol": "black", "top": "short tee", "topcol": "brown", "url": "https://smart-wardrobe-static.s3.amazonaws.com/mss/man/formal/17115.jpg"}, {"bottom": "chinos", "bottomcol": "black", "top": "short tee", "topcol": "olive", "url": "https://smart-wardrobe-static.s3.amazonaws.com/mss/man/formal/17145.jpg"}, {"outer": "vest", "outercol": "lightgray", "bottom": "long skirt", "bottomcol": "beige", "url": "https://smart-wardrobe-static.s3.amazonaws.com/mss/man/formal/17159.jpg"}, {"bottom": "chinos", "bottomcol": "lightgray", "top": "short tee", "topcol": "black", "url": "https://smart-wardrobe-static.s3.amazonaws.com/mss/man/formal/17180.jpg"}, {"bottom": "chinos", "bottomcol": "navy", "top": "long shirt", "topcol": "lightgray", "url": "https://smart-wardrobe-static.s3.amazonaws.com/mss/man/formal/17184.jpg"}, {"bottom": "chinos", "bottomcol": "lightgray", "url": "https://smart-wardrobe-static.s3.amazonaws.com/mss/man/formal/17215.jpg"}, {"bottom": "chinos", "bottomcol": "beige", "top": "short tee", "topcol": "beige", "url": "https://smart-wardrobe-static.s3.amazonaws.com/mss/man/formal/17216.jpg"}, {"top": "short tee", "topcol": "beige", "bottom": "sweatpants", "bottomcol": "black", "url": "https://smart-wardrobe-static.s3.amazonaws.com/mss/man/formal/17254.jpg"}, {"bottom": "shorts", "bottomcol": "black", "top": "short tee", "topcol": "blue", "url": "https://smart-wardrobe-static.s3.amazonaws.com/mss/man/formal/17286.jpg"}, {"bottom": "shorts", "bottomcol": "lightgray", "top": "short tee", "topcol": "beige", "url": "https://smart-wardrobe-static.s3.amazonaws.com/mss/man/formal/17289.jpg"}, {"top": "short tee", "topcol": "darkgray", "bottom": "short skirt", "bottomcol": "darkgray", "url": "https://smart-wardrobe-static.s3.amazonaws.com/mss/man/formal/17331.jpg"}, {"bottom": "chinos", "bottomcol": "darkgray", "top": "short shirt", "topcol": "lightgray", "url": "https://smart-wardrobe-static.s3.amazonaws.com/mss/man/formal/17353.jpg"}, {"top": "short shirt", "topcol": "lightgray", "bottom": "shorts", "bottomcol": "darkgray", "url": "https://smart-wardrobe-static.s3.amazonaws.com/mss/man/formal/17359.jpg"}, {"bottom": "jeans", "bottomcol": "jean", "top": "short tee", "topcol": "black", "url": "https://smart-wardrobe-static.s3.amazonaws.com/mss/man/formal/17370.jpg"}, {"bottom": "shorts", "bottomcol": "lightgray", "top": "long shirt", "topcol": "lightgray", "url": "https://smart-wardrobe-static.s3.amazonaws.com/mss/man/formal/17471.jpg"}, {"bottom": "shorts", "bottomcol": "beige", "url": "https://smart-wardrobe-static.s3.amazonaws.com/mss/man/formal/17479.jpg"}, {"top": "long shirt", "topcol": "darkgray", "bottom": "shorts", "bottomcol": "olive", "url": "https://smart-wardrobe-static.s3.amazonaws.com/mss/man/formal/17481.jpg"}, {"top": "long shirt", "topcol": "lightgray", "bottom": "shorts", "bottomcol": "lightgray", "url": "https://smart-wardrobe-static.s3.amazonaws.com/mss/man/formal/17482.jpg"}, {"bottom": "chinos", "bottomcol": "black", "top": "short shirt", "topcol": "darkgray", "url": "https://smart-wardrobe-static.s3.amazonaws.com/mss/man/formal/17553.jpg"}, {"bottom": "chinos", "bottomcol": "darkgray", "url": "https://smart-wardrobe-static.s3.amazonaws.com/mss/man/formal/17567.jpg"}, {"bottom": "chinos", "bottomcol": "darkgray", "url": "https://smart-wardrobe-static.s3.amazonaws.com/mss/man/formal/17606.jpg"}, {"bottom": "chinos", "bottomcol": "darkgray", "url": "https://smart-wardrobe-static.s3.amazonaws.com/mss/man/formal/17611.jpg"}, {"bottom": "chinos", "bottomcol": "olive", "top": "short tee", "topcol": "beige", "url": "https://smart-wardrobe-static.s3.amazonaws.com/mss/man/formal/17649.jpg"}, {"top": "long blouse", "topcol": "blue", "url": "https://smart-wardrobe-static.s3.amazonaws.com/mss/man/formal/17654.jpg"}, {"bottom": "chinos", "bottomcol": "darkgray", "top": "long shirt", "topcol": "beige", "url": "https://smart-wardrobe-static.s3.amazonaws.com/mss/man/formal/17765.jpg"}, {"outer": "blazer", "outercol": "darkgray", "top": "long shirt", "topcol": "lightgray", "bottom": "shorts", "bottomcol": "darkgray", "url": "https://smart-wardrobe-static.s3.amazonaws.com/mss/man/formal/17798.jpg"}, {"bottom": "jeans", "bottomcol": "jean", "top": "long blouse", "topcol": "black", "url": "https://smart-wardrobe-static.s3.amazonaws.com/mss/man/formal/17803.jpg"}, {"dress": "jumpsuit", "dresscol": "black", "top": "long tee", "topcol": "darkgray", "url": "https://smart-wardrobe-static.s3.amazonaws.com/mss/man/formal/17809.jpg"}, {"bottom": "chinos", "bottomcol": "beige", "top": "short tee", "topcol": "olive", "url": "https://smart-wardrobe-static.s3.amazonaws.com/mss/man/formal/17810.jpg"}, {"bottom": "chinos", "bottomcol": "blue", "top": "long shirt", "topcol": "darkgray", "url": "https://smart-wardrobe-static.s3.amazonaws.com/mss/man/formal/17811.jpg"}, {"bottom": "chinos", "bottomcol": "brown", "top": "long shirt", "topcol": "lightgray", "url": "https://smart-wardrobe-static.s3.amazonaws.com/mss/man/formal/17813.jpg"}, {"bottom": "chinos", "bottomcol": "darkgray", "outer": "bomber", "outercol": "darkgray", "top": "long shirt", "topcol": "lightgray", "url": "https://smart-wardrobe-static.s3.amazonaws.com/mss/man/formal/17865.jpg"}, {"bottom": "chinos", "bottomcol": "darkgray", "top": "long shirt", "topcol": "darkgray", "url": "https://smart-wardrobe-static.s3.amazonaws.com/mss/man/formal/17935.jpg"}, {"bottom": "chinos", "bottomcol": "olive", "url": "https://smart-wardrobe-static.s3.amazonaws.com/mss/man/formal/17958.jpg"}, {"bottom": "sweatpants", "bottomcol": "darkgray", "outer": "leather", "outercol": "beige", "top": "long shirt", "topcol": "darkgray", "url": "https://smart-wardrobe-static.s3.amazonaws.com/mss/man/formal/17959.jpg"}, {"bottom": "jeans", "bottomcol": "lightjean", "url": "https://smart-wardrobe-static.s3.amazonaws.com/mss/man/formal/17976.jpg"}]